ben_good/__init__.py
ben_good-0.1.0.dist-info/WHEEL
ben_good-0.1.0.dist-info/entry_points.txt
ben_good-0.1.0.dist-info/METADATA
ben_good-0.1.0.dist-info/RECORD
