Metadata-Version: 2.3
Name: ben-good
Version: 0.1.0
Summary: Add your description here
Author: ben
Author-email: ben <2014911413@qq.com>
Requires-Dist: mcp[cli]>=1.20.0
Requires-Dist: fastmcp>=2.13.0.2
Requires-Python: >=3.12
